<?xml version="1.0"?>
<annotation>
    <folder>images</folder>
    <filename>6.png</filename>
    <path>images/6.png</path>
    <source>
        <database>Unknown</database>
    </source>
    <size>
        <width>1024</width>
        <height>1024</height>
        <depth>3</depth>
    </size>
    <segmented>0</segmented>
    <object>
        <name>Void</name>
        <pose>Unspecified</pose>
        <truncated>0</truncated>
        <difficult>0</difficult>
        <bndbox>
            <xmin>807.4999999999997</xmin>
            <ymin>704.9999999999998</ymin>
            <xmax>1017.4999999999995</xmax>
            <ymax>1034.9999999999995</ymax>
        </bndbox>
    </object>
    <object>
        <name>Other</name>
        <pose>Unspecified</pose>
        <truncated>0</truncated>
        <difficult>0</difficult>
        <bndbox>
            <xmin>839.9999999999997</xmin>
            <ymin>582.4999999999998</ymin>
            <xmax>1014.9999999999995</xmax>
            <ymax>722.4999999999998</ymax>
        </bndbox>
    </object>
    <object>
        <name>Void</name>
        <pose>Unspecified</pose>
        <truncated>0</truncated>
        <difficult>0</difficult>
        <bndbox>
            <xmin>2.499999999999999</xmin>
            <ymin>969.9999999999997</ymin>
            <xmax>214.99999999999991</xmax>
            <ymax>1029.9999999999995</ymax>
        </bndbox>
    </object>
    <object>
        <name>Other</name>
        <pose>Unspecified</pose>
        <truncated>0</truncated>
        <difficult>0</difficult>
        <bndbox>
            <xmin>17.499999999999993</xmin>
            <ymin>812.4999999999997</ymin>
            <xmax>164.99999999999994</xmax>
            <ymax>969.9999999999995</ymax>
        </bndbox>
    </object>
    <object>
        <name>Void</name>
        <pose>Unspecified</pose>
        <truncated>0</truncated>
        <difficult>0</difficult>
        <bndbox>
            <xmin>402.49999999999983</xmin>
            <ymin>0</ymin>
            <xmax>704.9999999999998</xmax>
            <ymax>264.9999999999999</ymax>
        </bndbox>
    </object>
    <object>
        <name>Void</name>
        <pose>Unspecified</pose>
        <truncated>0</truncated>
        <difficult>0</difficult>
        <bndbox>
            <xmin>929.9999999999997</xmin>
            <ymin>7.499999999999997</ymin>
            <xmax>1017.4999999999997</xmax>
            <ymax>159.99999999999994</ymax>
        </bndbox>
    </object>
    <object>
        <name>Other</name>
        <pose>Unspecified</pose>
        <truncated>0</truncated>
        <difficult>0</difficult>
        <bndbox>
            <xmin>902.4999999999997</xmin>
            <ymin>119.99999999999996</ymin>
            <xmax>1019.9999999999997</xmax>
            <ymax>257.4999999999999</ymax>
        </bndbox>
    </object>
    <object>
        <name>Other</name>
        <pose>Unspecified</pose>
        <truncated>0</truncated>
        <difficult>0</difficult>
        <bndbox>
            <xmin>139.99999999999994</xmin>
            <ymin>519.9999999999998</ymin>
            <xmax>272.4999999999999</xmax>
            <ymax>637.4999999999998</ymax>
        </bndbox>
    </object>
    <object>
        <name>Other</name>
        <pose>Unspecified</pose>
        <truncated>0</truncated>
        <difficult>0</difficult>
        <bndbox>
            <xmin>454.99999999999983</xmin>
            <ymin>532.4999999999998</ymin>
            <xmax>572.4999999999998</xmax>
            <ymax>597.4999999999998</ymax>
        </bndbox>
    </object>
    <object>
        <name>Other</name>
        <pose>Unspecified</pose>
        <truncated>0</truncated>
        <difficult>0</difficult>
        <bndbox>
            <xmin>174.99999999999994</xmin>
            <ymin>659.9999999999998</ymin>
            <xmax>277.4999999999999</xmax>
            <ymax>699.9999999999998</ymax>
        </bndbox>
    </object>
    <object>
        <name>Void</name>
        <pose>Unspecified</pose>
        <truncated>0</truncated>
        <difficult>0</difficult>
        <bndbox>
            <xmin>0</xmin>
            <ymin>2.499999999999999</ymin>
            <xmax>67.49999999999997</xmax>
            <ymax>52.499999999999986</ymax>
        </bndbox>
    </object>
    <object>
        <name>Point</name>
        <pose>Unspecified</pose>
        <truncated>0</truncated>
        <difficult>0</difficult>
        <bndbox>
            <xmin>236.25</xmin>
            <ymin>175</ymin>
            <xmax>275</xmax>
            <ymax>212.5</ymax>
        </bndbox>
    </object>
    <object>
        <name>Point</name>
        <pose>Unspecified</pose>
        <truncated>0</truncated>
        <difficult>0</difficult>
        <bndbox>
            <xmin>628.75</xmin>
            <ymin>363.75</ymin>
            <xmax>650</xmax>
            <ymax>387.5</ymax>
        </bndbox>
    </object>
    <object>
        <name>Point</name>
        <pose>Unspecified</pose>
        <truncated>0</truncated>
        <difficult>0</difficult>
        <bndbox>
            <xmin>495</xmin>
            <ymin>303.75</ymin>
            <xmax>523.75</xmax>
            <ymax>341.25</ymax>
        </bndbox>
    </object>
    <object>
        <name>Point</name>
        <pose>Unspecified</pose>
        <truncated>0</truncated>
        <difficult>0</difficult>
        <bndbox>
            <xmin>660</xmin>
            <ymin>871.25</ymin>
            <xmax>680</xmax>
            <ymax>910</ymax>
        </bndbox>
    </object>
</annotation>